helloworld.py
hello_sumu-0.0.1.dist-info/DESCRIPTION.rst
hello_sumu-0.0.1.dist-info/METADATA
hello_sumu-0.0.1.dist-info/RECORD
hello_sumu-0.0.1.dist-info/WHEEL
hello_sumu-0.0.1.dist-info/metadata.json
hello_sumu-0.0.1.dist-info/top_level.txt
