Metadata-Version: 2.0
Name: hello-sumu
Version: 0.0.1
Summary: greet
Home-page: https://www.youtube.com/watch?v=QgZ7qv4Cd0Y
Author: Sumu
Author-email: suman.sumanshekhar698@gmail.com
License: UNKNOWN
Platform: UNKNOWN
